{
  "event_id": "daa111296b85",
  "ticker": "ALVO",
  "company_name": "Alvotech",
  "drug_name": "AVT05",
  "result": "crl",
  "pdufa_date": "2025-12-31",
  "approval_type": {
    "status": "found",
    "value": "bla",
    "source": "websearch:AVT05-GL-C01 Phase 3 (BLA pending Q4 2025)",
    "confidence": 0.9,
    "evidence": [],
    "searched_sources": [
      "websearch"
    ],
    "last_searched": "2026-01-09T21:20:41.095635",
    "error": null
  },
  "indication": {
    "status": "found",
    "value": "Rheumatoid arthritis (biosimilar to Simponi/golimumab)",
    "source": "websearch:AVT05-GL-C01 Phase 3 (BLA pending Q4 2025)",
    "confidence": 0.85,
    "evidence": [],
    "searched_sources": [
      "websearch"
    ],
    "last_searched": "2026-01-09T21:20:41.095636",
    "error": null
  },
  "generic_name": {
    "status": "found",
    "value": "golimumab biosimilar",
    "source": "websearch_fda",
    "confidence": 0.85,
    "tier": 2,
    "searched_sources": [
      "websearch"
    ],
    "last_searched": "2026-01-10T00:11:33.226880",
    "error": null
  },
  "therapeutic_area": {
    "status": "found",
    "value": "Rheumatology",
    "source": "websearch",
    "confidence": 0.85,
    "tier": 2,
    "evidence": [],
    "searched_sources": [
      "websearch"
    ],
    "last_searched": "2026-01-10T10:49:58.440564",
    "error": null
  },
  "mechanism_of_action": {
    "status": "found",
    "value": "CD20 inhibitor (biosimilar)",
    "source": "legacy_migration",
    "confidence": 0.75,
    "tier": 3,
    "evidence": [],
    "searched_sources": [
      "legacy_v12"
    ],
    "last_searched": "2026-01-10T12:42:32.003285",
    "error": null,
    "note": null
  },
  "phase": {
    "status": "found",
    "value": "Phase 3",
    "source": "websearch_clinical",
    "confidence": 0.85,
    "tier": 2,
    "searched_sources": [
      "websearch"
    ],
    "last_searched": "2026-01-10T00:11:33.226880",
    "error": null
  },
  "primary_endpoint_met": {
    "status": "found",
    "value": true,
    "source": "websearch:AVT05-GL-C01 Phase 3 (BLA pending Q4 2025)",
    "confidence": 0.9,
    "evidence": [
      "AVT05-GL-C01 Phase 3 (BLA pending Q4 2025)"
    ],
    "searched_sources": [
      "websearch"
    ],
    "last_searched": "2026-01-09T21:20:41.095621",
    "error": null
  },
  "p_value": {
    "status": "found",
    "value": "biosimilar",
    "source": "websearch",
    "confidence": 0.85,
    "trial": null,
    "tier": 2,
    "note": "No numeric p-value applicable"
  },
  "effect_size": {
    "status": "found",
    "value": "LSM difference within equivalence margin (DAS28-CRP)",
    "source": "websearch:AVT05-GL-C01 Phase 3 (BLA pending Q4 2025)",
    "confidence": 0.85,
    "evidence": [],
    "searched_sources": [
      "websearch"
    ],
    "last_searched": "2026-01-09T21:20:41.095631",
    "error": null
  },
  "has_prior_crl": {
    "status": "found",
    "value": true,
    "source": "legacy_v12",
    "confidence": 0.75,
    "evidence": [],
    "searched_sources": [
      "legacy_v12"
    ],
    "last_searched": null,
    "error": null
  },
  "is_resubmission": {
    "status": "found",
    "value": 1,
    "source": "legacy_v12",
    "confidence": 0.75,
    "evidence": [],
    "searched_sources": [
      "legacy_v12"
    ],
    "last_searched": null,
    "error": null
  },
  "pai_passed": {
    "status": "found",
    "value": false,
    "source": "derived_from_crl_reason",
    "confidence": 0.85,
    "tier": 2
  },
  "warning_letter": {
    "status": "found",
    "value": false,
    "source": "derived_from_crl_reason",
    "confidence": 0.75,
    "tier": 2
  },
  "safety_signal": {
    "status": "found",
    "value": false,
    "source": "derived_from_crl_reason",
    "confidence": 0.85,
    "tier": 2
  },
  "p_value_numeric": null,
  "nct_ids": [
    "NCT02260791"
  ],
  "phase3_study_names": [
    "A Randomised, Blinded, Active-Controlled Study to Compare FKB327 Efficacy and Safety With the Comparator Humira® in Rheumatoid Arthritis Patients Inadequately Controlled on Methotrexate"
  ],
  "prior_crl_reason": {
    "status": "found",
    "value": "Manufacturing facility inspection deficiencies at Reykjavik",
    "source": "web_search",
    "category": "CMC_ISSUE",
    "confidence": 0.9,
    "tier": 2
  },
  "enrollment": {
    "value": 728,
    "status": "found",
    "source": "clinicaltrials.gov",
    "confidence": 0.95,
    "tier": 2
  },
  "fda_designations": {
    "breakthrough_therapy": false,
    "fast_track": false,
    "priority_review": false,
    "orphan_drug": false,
    "accelerated_approval": false
  },
  "adcom_info": {
    "scheduled": false,
    "held": false,
    "date": null,
    "outcome": null,
    "vote_for": null,
    "vote_against": null
  },
  "is_single_arm": {
    "value": false,
    "status": "found",
    "source": "clinicaltrials.gov",
    "confidence": 0.95,
    "tier": 2,
    "evidence": [
      "interventionModel=PARALLEL",
      "allocation=RANDOMIZED"
    ],
    "searched_sources": [
      "clinicaltrials.gov"
    ],
    "last_searched": "2026-01-11T08:28:16.578499",
    "error": null,
    "note": null,
    "has_value": true,
    "needs_retry": false,
    "is_complete": true
  },
  "trial_region": {
    "value": "global",
    "status": "found",
    "source": "clinicaltrials.gov",
    "confidence": 0.95,
    "tier": 2,
    "evidence": [
      "countries=['CANADA', 'CHILE', 'GERMANY', 'ROMANIA', 'PERU']..."
    ],
    "searched_sources": [
      "clinicaltrials.gov"
    ],
    "last_searched": "2026-01-11T08:28:16.578537",
    "error": null,
    "note": null,
    "has_value": true,
    "needs_retry": false,
    "is_complete": true
  },
  "is_biosimilar": {
    "value": true,
    "status": "found",
    "source": "generic_name_contains_biosimilar",
    "confidence": 0.95,
    "tier": 2,
    "evidence": [
      "generic_name contains biosimilar: golimumab biosimilar"
    ],
    "searched_sources": [
      "known_db",
      "patterns",
      "suffix_pattern",
      "approval_type"
    ],
    "last_searched": "2026-01-10T23:29:31.258651",
    "error": null,
    "note": null,
    "has_value": true,
    "needs_retry": false,
    "is_complete": true
  },
  "is_first_in_class": {
    "status": "not_searched",
    "value": null,
    "source": "",
    "confidence": 0.0,
    "tier": null,
    "evidence": [],
    "searched_sources": [],
    "last_searched": null,
    "error": null,
    "note": null
  },
  "crl_reason_type": {
    "status": "found",
    "value": "cmc",
    "source": "derived_from_prior_crl_reason",
    "confidence": 0.9,
    "tier": 2,
    "evidence": [
      "Manufacturing facility inspection deficiencies"
    ],
    "searched_sources": [
      "prior_crl_reason"
    ],
    "last_searched": "2026-01-11T13:07:35.280278",
    "error": null,
    "note": null
  },
  "warning_letter_date": {
    "value": null,
    "status": "confirmed_none",
    "source": "websearch_fda",
    "confidence": 0.7,
    "tier": 3,
    "evidence": [
      "No FDA warning letter found in search"
    ],
    "searched_sources": [
      "websearch_fda"
    ],
    "last_searched": "2026-01-11T04:13:16.580522",
    "error": null
  },
  "fda_483_date": {
    "status": "not_searched",
    "value": null,
    "source": "",
    "confidence": 0.0,
    "tier": null,
    "evidence": [],
    "searched_sources": [],
    "last_searched": null,
    "error": null,
    "note": null
  },
  "fda_483_observations": {
    "status": "not_searched",
    "value": null,
    "source": "",
    "confidence": 0.0,
    "tier": null,
    "evidence": [],
    "searched_sources": [],
    "last_searched": null,
    "error": null,
    "note": null
  },
  "cdmo_name": {
    "status": "not_searched",
    "value": null,
    "source": "",
    "confidence": 0.0,
    "tier": null,
    "evidence": [],
    "searched_sources": [],
    "last_searched": null,
    "error": null,
    "note": null
  },
  "pai_date": {
    "value": null,
    "status": "not_found",
    "source": "",
    "confidence": 0.0,
    "tier": null,
    "evidence": [],
    "searched_sources": [
      "websearch"
    ],
    "last_searched": "2026-01-10T13:30:37.765624",
    "error": null,
    "note": null,
    "has_value": false,
    "needs_retry": true,
    "is_complete": false
  },
  "clinical_hold_history": {
    "value": null,
    "status": "confirmed_none",
    "source": "websearch_clinical_hold",
    "confidence": 0.0,
    "tier": null,
    "evidence": [],
    "searched_sources": [
      "websearch_clinical_hold"
    ],
    "last_searched": "2026-01-10T13:30:38.710579",
    "error": null,
    "note": null,
    "has_value": false,
    "needs_retry": false,
    "is_complete": true
  },
  "days_to_pdufa": -10,
  "pdufa_status": "past",
  "risk_tier": "HIGH",
  "days_calculated_at": "2026-01-10T16:59:37.160208",
  "original_case_id": "ef4c5122b5b5",
  "data_quality_score": 0.15,
  "collected_at": "2026-01-09T08:51:56.265747",
  "enriched_at": "2026-01-11T17:32:47.490345",
  "needs_manual_review": false,
  "review_reasons": [],
  "migrated_at": "2026-01-10T12:42:32.003306",
  "schema_version": "3.0",
  "adcom_scheduled": {
    "value": false,
    "status": "confirmed_none",
    "source": "websearch_adcom",
    "confidence": 0.7,
    "tier": 3,
    "evidence": [],
    "searched_sources": [
      "websearch_adcom"
    ],
    "last_searched": "2026-01-11T08:32:47.490335"
  },
  "adcom_vote_ratio": {
    "value": null,
    "status": "not_applicable",
    "source": "websearch_adcom",
    "confidence": 0.6,
    "tier": 3,
    "evidence": [],
    "searched_sources": [
      "websearch_adcom"
    ],
    "last_searched": "2026-01-11T08:32:47.490342"
  },
  "breakthrough_therapy": {
    "value": null,
    "status": "not_found",
    "source": "websearch",
    "confidence": 0.0,
    "tier": 3,
    "evidence": [],
    "searched_sources": [
      "websearch"
    ],
    "last_searched": "2026-01-11T17:27:19.650777",
    "search_status": "CONFIRMED_NONE"
  },
  "priority_review": {
    "value": null,
    "status": "not_found",
    "source": "websearch",
    "confidence": 0.0,
    "tier": 3,
    "evidence": [],
    "searched_sources": [
      "websearch"
    ],
    "last_searched": "2026-01-11T17:27:32.449569",
    "search_status": "CONFIRMED_NONE"
  },
  "fast_track": {
    "value": null,
    "status": "not_found",
    "source": "websearch",
    "confidence": 0.0,
    "tier": 3,
    "evidence": [],
    "searched_sources": [
      "websearch"
    ],
    "last_searched": "2026-01-11T17:27:38.853228",
    "search_status": "CONFIRMED_NONE"
  },
  "orphan_drug": {
    "value": null,
    "status": "not_found",
    "source": "websearch",
    "confidence": 0.0,
    "tier": 3,
    "evidence": [],
    "searched_sources": [
      "websearch"
    ],
    "last_searched": "2026-01-11T17:27:26.099209",
    "search_status": "CONFIRMED_NONE"
  },
  "accelerated_approval": {
    "value": null,
    "status": "not_found",
    "source": "websearch",
    "confidence": 0.0,
    "tier": 3,
    "evidence": [],
    "searched_sources": [
      "websearch"
    ],
    "last_searched": "2026-01-11T17:27:45.362134",
    "search_status": "CONFIRMED_NONE"
  }
}